iatiflattener/__init__.py
iatiflattener/data_quality.py
iatiflattener/group_data.py
iatiflattener/model.py
iatiflattener/lib/__init__.py
iatiflattener/lib/iati_budget_helpers.py
iatiflattener/lib/iati_helpers.py
iatiflattener/lib/iati_transaction_helpers.py
iatiflattener/lib/utils.py
iatiflattener/lib/variables.py
iatiflattener/tests/__init__.py
iatiflattener/tests/test_activity.py
iatiflattener/tests/test_budget.py
iatiflattener/tests/test_csv.py
iatiflattener/tests/test_transaction.py
iatiflattener-0.10.11.dist-info/LICENSE
iatiflattener-0.10.11.dist-info/METADATA
iatiflattener-0.10.11.dist-info/WHEEL
iatiflattener-0.10.11.dist-info/namespace_packages.txt
iatiflattener-0.10.11.dist-info/top_level.txt
iatiflattener-0.10.11.dist-info/RECORD
